scrapwiki/WikipediaPage.py
scrapwiki/__init__.py
scrapwiki-0.0.2.dist-info/LICENSE
scrapwiki-0.0.2.dist-info/METADATA
scrapwiki-0.0.2.dist-info/WHEEL
scrapwiki-0.0.2.dist-info/top_level.txt
scrapwiki-0.0.2.dist-info/RECORD
