Metadata-Version: 2.1
Name: scrapwiki
Version: 0.0.2
Summary: Scrap Wikipedia page. Fetch title, paragraph or entire page html
Author: Krittipoom Phalachun
Author-email: krittipoom@outlook.com
Classifier: Intended Audience :: Developers
Classifier: Programming Language :: Python :: 3
Classifier: License :: OSI Approved :: MIT License
Classifier: Operating System :: OS Independent
Requires-Python: >=3.8
License-File: LICENSE
